pki/__init__.py
pki/admin.py
pki/email.py
pki/forms.py
pki/graphviz.py
pki/helper.py
pki/middleware.py
pki/models.py
pki/openssl.py
pki/settings.py
pki/urls.py
pki/version.py
pki/views.py
pki/fixtures/eku_and_ku.json
pki/migrations/0001_initial.py
pki/migrations/__init__.py
pki/migrations/__pycache__/0001_initial.cpython-36.pyc
pki/migrations/__pycache__/__init__.cpython-36.pyc
pki/migrations/__pycache__/crlnumber
pki/migrations/__pycache__/crlnumber.old
pki/migrations/__pycache__/index.txt
pki/migrations/__pycache__/index.txt.attr
pki/migrations/__pycache__/index.txt.attr.old
pki/migrations/__pycache__/index.txt.old
pki/migrations/__pycache__/main-chain.cert.pem
pki/migrations/__pycache__/serial
pki/migrations/__pycache__/serial.old
pki/migrations/__pycache__/certs/01.pem
pki/migrations/__pycache__/certs/02.pem
pki/migrations/__pycache__/certs/main.cert.pem
pki/migrations/__pycache__/certs/test1.cert.pem
pki/migrations/__pycache__/certs/test1.csr.pem
pki/migrations/__pycache__/certs/test1.key.pem
pki/migrations/__pycache__/crl/main.crl.pem
pki/migrations/__pycache__/private/main.key.pem
pki/static/css/pki.css
pki/static/css/tipsy.css
pki/static/img/blue-document-tree.png
pki/static/img/blue-document-tree_bw.png
pki/static/img/chain.png
pki/static/img/clock-frame.png
pki/static/img/drive-download.png
pki/static/img/drive-download_bw.png
pki/static/img/icon-no.gif
pki/static/img/icon-yes.gif
pki/static/img/mag.png
pki/static/img/mag_disabled.png
pki/static/img/mail--arrow.png
pki/static/img/mail--arrow_bw.png
pki/static/img/mail--exclamation.png
pki/static/img/minus.png
pki/static/img/plus.png
pki/static/img/tipsy.gif
pki/static/img/tree.png
pki/static/img/tree_disabled.png
pki/static/js/delete_detail.js
pki/static/js/delete_detail.min.js
pki/static/js/jquery-1.5.min.js
pki/static/js/jquery.js
pki/static/js/jquery.tipsy.js
pki/static/js/pki_admin.js
pki/static/js/pki_admin.min.js
pki/static/pki/css/tipsy.css
pki/templates/404.html
pki/templates/500.html
django3_pki-0.0.4.dist-info/LICENSE
django3_pki-0.0.4.dist-info/METADATA
django3_pki-0.0.4.dist-info/WHEEL
django3_pki-0.0.4.dist-info/top_level.txt
django3_pki-0.0.4.dist-info/RECORD
