Metadata-Version: 2.1
Name: django3-pki
Version: 0.0.4
Summary: Django application for manage                your own certificate center
Home-page: https://github.com/yaricp/django3-pki
Author: Yaric Pisarev
Author-email: yaricp@gmail.com
License: UNKNOWN
Platform: UNKNOWN
Classifier: Programming Language :: Python :: 3
Classifier: License :: OSI Approved :: MIT License
Classifier: Operating System :: OS Independent
Requires-Python: >=3.6
